README.md
setup.py
mfp2sheets.egg-info/PKG-INFO
mfp2sheets.egg-info/SOURCES.txt
mfp2sheets.egg-info/dependency_links.txt
mfp2sheets.egg-info/entry_points.txt
mfp2sheets.egg-info/requires.txt
mfp2sheets.egg-info/top_level.txt
src/__init__.py
src/mfp_sheets.py
src/version.py